README.md
setup.py
nans_are_numbers/__init__.py
nans_are_numbers/_version.py
nans_are_numbers/core_float_utils.py
nans_are_numbers/nans.py
nans_are_numbers.egg-info/PKG-INFO
nans_are_numbers.egg-info/SOURCES.txt
nans_are_numbers.egg-info/dependency_links.txt
nans_are_numbers.egg-info/top_level.txt