Metadata-Version: 2.1
Name: nans-are-numbers
Version: 1.0.3
Summary: An esoteric data type built entirely of NaNs
Home-page: https://github.com/thoppe/NansAreNumbers
Author: Travis Hoppe
Author-email: travis.hoppe+{package_name}@gmail.com
License: CC-SA
Keywords: art,math
Platform: UNKNOWN
Classifier: Development Status :: 4 - Beta
Classifier: Intended Audience :: Developers
Classifier: Intended Audience :: Other Audience
Classifier: Intended Audience :: Science/Research
Classifier: Topic :: Artistic Software
Classifier: Programming Language :: Python :: 3
